[[
  "1",
  "2",
  "3",
  "4",
  "5"
],{
  "id": "6",
  "title": "7",
  "author": "8",
  "genre": "9",
  "owner": "10",
  "isAvailable": false,
  "reviews": "11",
  "image": null,
  "ownerHistory": "12"
},{
  "id": "13",
  "title": "14",
  "author": "15",
  "genre": "9",
  "owner": "16",
  "isAvailable": false,
  "reviews": "17",
  "image": null,
  "ownerHistory": "18"
},{
  "id": "19",
  "title": "20",
  "author": "21",
  "genre": "22",
  "owner": "23",
  "isAvailable": false,
  "reviews": "24",
  "image": null,
  "ownerHistory": "25"
},{
  "id": "26",
  "title": "27",
  "author": "28",
  "genre": "9",
  "owner": "29",
  "isAvailable": false,
  "reviews": "30",
  "image": null,
  "ownerHistory": "31"
},{
  "id": "32",
  "title": "33",
  "author": "34",
  "genre": "35",
  "owner": "36",
  "isAvailable": false,
  "reviews": "37",
  "image": null,
  "ownerHistory": "38"
},"b6fe8f1b-c9ea-4474-aee8-d7299a0beede","Harry Potter","J.K. Rowling","Fantasy",{
  "id": "39",
  "username": "40",
  "email": "41",
  "password": "42",
  "ownedBooks": "43"
},[],[
  "10"
],"8ceaa9ec-95fd-450c-914c-b266b9c32393","Lord of the Rings","J.R.R. Tolkien",{
  "id": "44",
  "username": "45",
  "email": "46",
  "password": "47",
  "ownedBooks": "48"
},[],[
  "16"
],"bc3a281c-33b6-457b-b255-c4a200f1ed43","The Great Gatsby","F. Scott Fitzgerald","Classic",{
  "id": "49",
  "username": "50",
  "email": "51",
  "password": "52",
  "ownedBooks": "53"
},[],[
  "23"
],"9567c070-8b20-437d-8a82-92cdd336729b","Game of Thrones","George R.R. Martin",{
  "id": "39",
  "username": "40",
  "email": "41",
  "password": "42",
  "ownedBooks": "54"
},[],[
  "29"
],"329f6924-d393-4c5d-a0c4-535d37dd445d","To Kill a Mockingbird","Harper Lee","Fiction",{
  "id": "44",
  "username": "45",
  "email": "46",
  "password": "47",
  "ownedBooks": "55"
},[],[
  "36"
],"efc6708d-a4b5-46d9-8f36-f17c364cc87e","john","john@example.com","john123",[
  "56"
],"be29c6c3-12cf-4573-b3b0-1afcbe8de7df","cagri","cagri@example.com","securepassword",[
  "57"
],"ce3b4d59-43ee-49ba-92f8-4ed6e7f0997e","zeynep","zeynep@example.com","zeyno",[
  "58"
],[
  "59",
  "60"
],[
  "61",
  "62"
],{
  "id": "6",
  "title": "7",
  "author": "8",
  "genre": "9",
  "owner": "10",
  "isAvailable": false,
  "reviews": "11",
  "image": null,
  "ownerHistory": "12"
},{
  "id": "13",
  "title": "14",
  "author": "15",
  "genre": "9",
  "owner": "16",
  "isAvailable": false,
  "reviews": "17",
  "image": null,
  "ownerHistory": "18"
},{
  "id": "19",
  "title": "20",
  "author": "21",
  "genre": "22",
  "owner": "23",
  "isAvailable": false,
  "reviews": "24",
  "image": null,
  "ownerHistory": "25"
},{
  "id": "6",
  "title": "7",
  "author": "8",
  "genre": "9",
  "owner": "63",
  "isAvailable": false,
  "reviews": "64",
  "image": null,
  "ownerHistory": "65"
},{
  "id": "26",
  "title": "27",
  "author": "28",
  "genre": "9",
  "owner": "29",
  "isAvailable": false,
  "reviews": "30",
  "image": null,
  "ownerHistory": "31"
},{
  "id": "13",
  "title": "14",
  "author": "15",
  "genre": "9",
  "owner": "66",
  "isAvailable": false,
  "reviews": "67",
  "image": null,
  "ownerHistory": "68"
},{
  "id": "32",
  "title": "33",
  "author": "34",
  "genre": "35",
  "owner": "36",
  "isAvailable": false,
  "reviews": "37",
  "image": null,
  "ownerHistory": "38"
},{
  "id": "39",
  "username": "40",
  "email": "41",
  "password": "42",
  "ownedBooks": "54"
},[],[
  "63"
],{
  "id": "44",
  "username": "45",
  "email": "46",
  "password": "47",
  "ownedBooks": "55"
},[],[
  "66"
]]